electre/__init__.py
electre/electre.py
electre-0.0.5.dist-info/LICENSE
electre-0.0.5.dist-info/METADATA
electre-0.0.5.dist-info/WHEEL
electre-0.0.5.dist-info/top_level.txt
electre-0.0.5.dist-info/RECORD
